{"_type":"export","__export_format":4,"__export_date":"2023-10-31T21:25:46.072Z","__export_source":"insomnia.desktop.app:v8.3.0","resources":[{"_id":"req_118195ec93d943f296b1efdacebacbfa","parentId":"fld_f317561159264bf1ad7a9b35a3bcd36e","modified":1698213909417,"created":1698213751605,"url":"http://127.0.0.1:4444/api/lockers/new","name":"New Request","description":"","method":"POST","body":{"mimeType":"application/json","text":"{\n\t\"City\": \"Veszprém\",\n\t\"Address\": \"Lajos utca 55.\",\n\t\"Capacity\": 12\n}"},"parameters":[],"headers":[{"name":"Content-Type","value":"application/json","id":"pair_4f1b43e8e3a5496582f8ed5de30580f3"},{"name":"User-Agent","value":"insomnia/8.3.0","id":"pair_d1476848be674f089a75e8f86bf861b9"},{"id":"pair_516fc601ace04332886a291f239a0daa","name":"Authorization","value":"eyJhbGciOiJIUzI1NiIsInR5cCI6IkpXVCJ9.eyJhY2Nlc3NfbGV2ZWwiOjMsImV4cCI6MTY5ODMwMDI5MiwidXNlcl9pZCI6NH0.ueGBBfY93VCNtr53oQ4ywiNJctL1Xkjsd1P4Ei4H1LY","description":""}],"authentication":{},"metaSortKey":-1694967641603,"isPrivate":false,"settingStoreCookies":true,"settingSendCookies":true,"settingDisableRenderRequestBody":false,"settingEncodeUrl":true,"settingRebuildPath":true,"settingFollowRedirects":"global","_type":"request"},{"_id":"fld_f317561159264bf1ad7a9b35a3bcd36e","parentId":"wrk_scratchpad","modified":1694965617948,"created":1694965617948,"name":"Lockers","description":"","environment":{},"environmentPropertyOrder":null,"metaSortKey":-1694965617948,"_type":"request_group"},{"_id":"wrk_scratchpad","parentId":null,"modified":1696234075095,"created":1696234075095,"name":"Scratch Pad","description":"","scope":"collection","_type":"workspace"},{"_id":"req_9cd77ade7b394f93bd28bbf77808126d","parentId":"fld_f317561159264bf1ad7a9b35a3bcd36e","modified":1697207108049,"created":1697207069834,"url":"http://127.0.0.1:4444/api/lockers/all","name":"List all lockers","description":"","method":"GET","body":{},"parameters":[],"headers":[{"name":"User-Agent","value":"insomnia/8.2.0"}],"authentication":{},"metaSortKey":-1694967641503,"isPrivate":false,"settingStoreCookies":true,"settingSendCookies":true,"settingDisableRenderRequestBody":false,"settingEncodeUrl":true,"settingRebuildPath":true,"settingFollowRedirects":"global","_type":"request"},{"_id":"req_d4f47d45e9d346a4a5f7827e411995b1","parentId":"fld_f317561159264bf1ad7a9b35a3bcd36e","modified":1694967701320,"created":1694967641403,"url":"http://127.0.0.1:4444/api/lockers/get-city/020003","name":"Get city from locker id (URL)","description":"","method":"GET","body":{},"parameters":[],"headers":[{"name":"User-Agent","value":"insomnia/2023.5.8"}],"authentication":{},"metaSortKey":-1694967641403,"isPrivate":false,"settingStoreCookies":true,"settingSendCookies":true,"settingDisableRenderRequestBody":false,"settingEncodeUrl":true,"settingRebuildPath":true,"settingFollowRedirects":"global","_type":"request"},{"_id":"req_06b70ecf8e3c4e54ac2567b3c55cbed8","parentId":"fld_f317561159264bf1ad7a9b35a3bcd36e","modified":1694967730527,"created":1694967722791,"url":"http://127.0.0.1:4444/api/lockers/get-packages/020003","name":"Get package from locker id (URL)","description":"","method":"GET","body":{},"parameters":[],"headers":[{"name":"User-Agent","value":"insomnia/2023.5.8"}],"authentication":{},"metaSortKey":-1694967481608,"isPrivate":false,"settingStoreCookies":true,"settingSendCookies":true,"settingDisableRenderRequestBody":false,"settingEncodeUrl":true,"settingRebuildPath":true,"settingFollowRedirects":"global","_type":"request"},{"_id":"req_74217a170ab7478f9c58c1cc84b38e10","parentId":"fld_f317561159264bf1ad7a9b35a3bcd36e","modified":1694967812748,"created":1694967762079,"url":"http://127.0.0.1:4444/api/lockers/get-fullness/010001","name":"Get locker fullness from locker id (URL)","description":"","method":"GET","body":{},"parameters":[],"headers":[{"name":"User-Agent","value":"insomnia/2023.5.8"}],"authentication":{},"metaSortKey":-1694967401710.5,"isPrivate":false,"settingStoreCookies":true,"settingSendCookies":true,"settingDisableRenderRequestBody":false,"settingEncodeUrl":true,"settingRebuildPath":true,"settingFollowRedirects":"global","_type":"request"},{"_id":"req_5a712723576f4ae2a8d0c3e075781ec0","parentId":"fld_7633b06afd0f4e77a264898d9ab74421","modified":1698213228481,"created":1698212502882,"url":"http://127.0.0.1:4444/api/users/set-accesslevel","name":"Set accesslevel","description":"","method":"POST","body":{"mimeType":"application/json","text":"{\n\t\"Email\": \"szalmag@mail.com\",\n\t\"AccessLevel\": 2\n}"},"parameters":[],"headers":[{"name":"Content-Type","value":"application/json","id":"pair_ce26591fe85445f9b1b73e941a21523b"},{"name":"User-Agent","value":"insomnia/8.3.0","id":"pair_cd3646c8f3954d08ab580b7ae8959dec"},{"id":"pair_b41d6dcddb2040b6b34dd05129742f94","name":"Authorization","value":"eyJhbGciOiJIUzI1NiIsInR5cCI6IkpXVCJ9.eyJhY2Nlc3NfbGV2ZWwiOjMsImV4cCI6MTY5ODI5OTYxOCwidXNlcl9pZCI6NH0.dUiK87QfLRSCSrUUNhCJVuAtsWM-DRQP_EGVlsh-ed0","description":""}],"authentication":{},"metaSortKey":-1694967322013,"isPrivate":false,"settingStoreCookies":true,"settingSendCookies":true,"settingDisableRenderRequestBody":false,"settingEncodeUrl":true,"settingRebuildPath":true,"settingFollowRedirects":"global","_type":"request"},{"_id":"fld_7633b06afd0f4e77a264898d9ab74421","parentId":"wrk_scratchpad","modified":1694965612846,"created":1694965612846,"name":"Users","description":"","environment":{},"environmentPropertyOrder":null,"metaSortKey":-1694965612846,"_type":"request_group"},{"_id":"req_41773571fb5c47219d52ae805b0ef5fd","parentId":"fld_7633b06afd0f4e77a264898d9ab74421","modified":1697189948798,"created":1697189744047,"url":"http://127.0.0.1:4444/api/users/all","name":"List all users","description":"","method":"GET","body":{},"parameters":[],"headers":[{"name":"User-Agent","value":"insomnia/8.2.0"}],"authentication":{},"metaSortKey":-1694967321913,"isPrivate":false,"settingStoreCookies":true,"settingSendCookies":true,"settingDisableRenderRequestBody":false,"settingEncodeUrl":true,"settingRebuildPath":true,"settingFollowRedirects":"global","_type":"request"},{"_id":"req_e807a841236142409288796a0bc1577e","parentId":"fld_7633b06afd0f4e77a264898d9ab74421","modified":1697733367343,"created":1694967321813,"url":"http://127.0.0.1:4444/api/users/register","name":"Register (JSON)","description":"","method":"POST","body":{"mimeType":"application/json","text":"{\n\t\"Name\": \"Teszt Elek\",\n\t\"Address\": \"Petőfi utca 4.\",\n\t\"Phone\": \"+36112233445\",\n\t\"Email\": \"telek@packx.hu\",\n\t\"Password\": \"T37eK!$7Ek#\",\n\t\"AccessLevel\": 1\n}"},"parameters":[],"headers":[{"name":"Content-Type","value":"application/json","id":"pair_25aa718418e847f2982c85b8e6865ec7"},{"name":"User-Agent","value":"insomnia/2023.5.8","id":"pair_7435cad42002446bbefe7d691e95c0ce"}],"authentication":{},"metaSortKey":-1694967321813,"isPrivate":false,"settingStoreCookies":true,"settingSendCookies":true,"settingDisableRenderRequestBody":false,"settingEncodeUrl":true,"settingRebuildPath":true,"settingFollowRedirects":"global","_type":"request"},{"_id":"req_f03d461801f74e7cb56770ff06259770","parentId":"fld_7633b06afd0f4e77a264898d9ab74421","modified":1696182051966,"created":1696181648551,"url":"http://127.0.0.1:4444/api/users/login","name":"Login","description":"","method":"POST","body":{"mimeType":"application/json","text":"{\n\t\"Email\": \"telek@test.hu\",\n\t\"Password\": \"T37eK!$7Ek#\"\n}"},"parameters":[],"headers":[{"name":"Content-Type","value":"application/json"},{"name":"User-Agent","value":"insomnia/8.1.0"}],"authentication":{},"metaSortKey":-1694966921050,"isPrivate":false,"settingStoreCookies":true,"settingSendCookies":true,"settingDisableRenderRequestBody":false,"settingEncodeUrl":true,"settingRebuildPath":true,"settingFollowRedirects":"global","_type":"request"},{"_id":"req_e89b20f142764edda3d6ef4fc8436eb3","parentId":"fld_7633b06afd0f4e77a264898d9ab74421","modified":1694967594087,"created":1694967568145,"url":"http://127.0.0.1:4444/api/users/get-accesslevel/3","name":"Get the access lecel of user (URL)","description":"","method":"GET","body":{},"parameters":[],"headers":[{"name":"User-Agent","value":"insomnia/2023.5.8"}],"authentication":{},"metaSortKey":-1694966520287,"isPrivate":false,"settingStoreCookies":true,"settingSendCookies":true,"settingDisableRenderRequestBody":false,"settingEncodeUrl":true,"settingRebuildPath":true,"settingFollowRedirects":"global","_type":"request"},{"_id":"req_541c42acae0e44ba8e681925cab66c72","parentId":"fld_7633b06afd0f4e77a264898d9ab74421","modified":1694967632233,"created":1694967623076,"url":"http://127.0.0.1:4444/api/users/2/packages","name":"Get packages from user (URL)","description":"","method":"GET","body":{},"parameters":[],"headers":[{"name":"User-Agent","value":"insomnia/2023.5.8"}],"authentication":{},"metaSortKey":-1694966119524,"isPrivate":false,"settingStoreCookies":true,"settingSendCookies":true,"settingDisableRenderRequestBody":false,"settingEncodeUrl":true,"settingRebuildPath":true,"settingFollowRedirects":"global","_type":"request"},{"_id":"req_4c68751ff33d4c3dbb1f6dd21ae79702","parentId":"fld_0ee2af5ae33e47718c90b22f378eb64d","modified":1698787462262,"created":1698786569200,"url":"http://127.0.0.1:4444/api/packages/courierpackages/1","name":"List packages based on courier ID","description":"","method":"GET","body":{},"parameters":[],"headers":[{"name":"User-Agent","value":"insomnia/8.3.0","id":"pair_2b622e0f345e4901828be03f4178bbe2"},{"id":"pair_dd9a775aab094f8e99bce4ae9b0c86fb","name":"Authorization","value":"eyJhbGciOiJIUzI1NiIsInR5cCI6IkpXVCJ9.eyJhY2Nlc3NfbGV2ZWwiOjMsImV4cCI6MTY5ODg3MzIyMywidXNlcl9pZCI6NH0.eLZ8U5Zs02o-4sJ2dZzdJrzYrD0eByxcR3BkfLFs2xw","description":""}],"authentication":{},"metaSortKey":-1694965718961,"isPrivate":false,"settingStoreCookies":true,"settingSendCookies":true,"settingDisableRenderRequestBody":false,"settingEncodeUrl":true,"settingRebuildPath":true,"settingFollowRedirects":"global","_type":"request"},{"_id":"fld_0ee2af5ae33e47718c90b22f378eb64d","parentId":"wrk_scratchpad","modified":1694965607100,"created":1694965607100,"name":"Packages","description":"","environment":{},"environmentPropertyOrder":null,"metaSortKey":-1694965607100,"_type":"request_group"},{"_id":"req_e1554475d1494cf9b706174ed277e77d","parentId":"fld_0ee2af5ae33e47718c90b22f378eb64d","modified":1698786025922,"created":1698784789599,"url":"http://127.0.0.1:4444/api/packages/statusup","name":"Change package status up","description":"","method":"POST","body":{"mimeType":"application/json","text":"{\n\t\"Package_ID\": 3\n}"},"parameters":[],"headers":[{"name":"Content-Type","value":"application/json","id":"pair_b219d1bacfcd492ca3e95fa9c1d8d451"},{"id":"pair_d28c0556cc4e46458f6f1d0b5d2608c5","name":"Authorization","value":"eyJhbGciOiJIUzI1NiIsInR5cCI6IkpXVCJ9.eyJhY2Nlc3NfbGV2ZWwiOjMsImV4cCI6MTY5ODg3MjQwNCwidXNlcl9pZCI6NH0._mCiDgvbXq9UavLBojLHPxbypMnIXeQxctAjGb7gm7s","description":""}],"authentication":{},"metaSortKey":-1694965718861,"isPrivate":false,"settingStoreCookies":true,"settingSendCookies":true,"settingDisableRenderRequestBody":false,"settingEncodeUrl":true,"settingRebuildPath":true,"settingFollowRedirects":"global","_type":"request"},{"_id":"req_08862253e143467dbb30e3817bb02a24","parentId":"fld_0ee2af5ae33e47718c90b22f378eb64d","modified":1698785423229,"created":1694965718761,"url":"http://127.0.0.1:4444/api/packages/new","name":"Add new package (JSON)","description":"","method":"POST","body":{"mimeType":"application/json","text":"{\n\t\"userID\": 2,\n\t\"senderLockerID\": \"020001\",\n\t\"destinationLockerID\": \"010003\",\n\t\"receiverName\": \"Kiss Béla János\",\n\t\"receiverEmail\": \"kbela@mail.com\",\n\t\"size\": \"Medium\",\n\t\"rapid\": true,\n\t\"note\": \"Törékeny\"\n}"},"parameters":[],"headers":[{"name":"Content-Type","value":"application/json","id":"pair_02825047512d407a8a0bbd5a7323917e"},{"name":"User-Agent","value":"insomnia/2023.5.8","id":"pair_245e3827734046cdb3058e6c20f0fad7"},{"id":"pair_ab7fe9e58f4441d5a1be615dc623236e","name":"Authorization","value":"eyJhbGciOiJIUzI1NiIsInR5cCI6IkpXVCJ9.eyJhY2Nlc3NfbGV2ZWwiOjMsImV4cCI6MTY5ODg3MTcyNSwidXNlcl9pZCI6NH0.knuHt5XYOSuDpLtMCft91pLGIVeIFmtDl0bcXiSSouE","description":""}],"authentication":{},"metaSortKey":-1694965718761,"isPrivate":false,"settingStoreCookies":true,"settingSendCookies":true,"settingDisableRenderRequestBody":false,"settingEncodeUrl":true,"settingRebuildPath":true,"settingFollowRedirects":"global","_type":"request"},{"_id":"req_522faaf9e4e0415d9deaabafec84e345","parentId":"fld_0ee2af5ae33e47718c90b22f378eb64d","modified":1694967262770,"created":1694967170625,"url":"http://127.0.0.1:4444/api/packages/change-status","name":"Change a package status (JSON)","description":"","method":"POST","body":{"mimeType":"application/json","text":"{\n\t\"Package_ID\": 2,\n\t\"Status_ID\": 1\n}"},"parameters":[],"headers":[{"name":"Content-Type","value":"application/json"},{"name":"User-Agent","value":"insomnia/2023.5.8"}],"authentication":{},"metaSortKey":-1694965712687.875,"isPrivate":false,"settingStoreCookies":true,"settingSendCookies":true,"settingDisableRenderRequestBody":false,"settingEncodeUrl":true,"settingRebuildPath":true,"settingFollowRedirects":"global","_type":"request"},{"_id":"req_7738fe03130e4686a1b7163db1c5305f","parentId":"fld_0ee2af5ae33e47718c90b22f378eb64d","modified":1694967309202,"created":1694967300594,"url":"http://127.0.0.1:4444/api/packages/cancel/2","name":"Cancel a package (URL)","description":"","method":"POST","body":{"mimeType":"application/json","text":""},"parameters":[],"headers":[{"name":"Content-Type","value":"application/json"},{"name":"User-Agent","value":"insomnia/2023.5.8"}],"authentication":{},"metaSortKey":-1694965709651.3125,"isPrivate":false,"settingStoreCookies":true,"settingSendCookies":true,"settingDisableRenderRequestBody":false,"settingEncodeUrl":true,"settingRebuildPath":true,"settingFollowRedirects":"global","_type":"request"},{"_id":"req_b4a3aacf200a45a5a2d280432436df7b","parentId":"fld_0ee2af5ae33e47718c90b22f378eb64d","modified":1698786019490,"created":1694967110621,"url":"http://127.0.0.1:4444/api/packages/getstatus/3","name":"Get a package status (URL)","description":"","method":"GET","body":{},"parameters":[],"headers":[{"name":"User-Agent","value":"insomnia/2023.5.8","id":"pair_2a7f3ce22e3c4774a619e35451ed71e0"},{"id":"pair_eb129dbb61f749d98a8cbf0b55f6cac1","name":"Authorization","value":"eyJhbGciOiJIUzI1NiIsInR5cCI6IkpXVCJ9.eyJhY2Nlc3NfbGV2ZWwiOjMsImV4cCI6MTY5ODg3MjMxNSwidXNlcl9pZCI6NH0.X70wcInJz-Tnfh4Pu4KB9RciwYWEIbTTVfOpfXhAeRk","description":""}],"authentication":{},"metaSortKey":-1694965706614.75,"isPrivate":false,"settingStoreCookies":true,"settingSendCookies":true,"settingDisableRenderRequestBody":false,"settingEncodeUrl":true,"settingRebuildPath":true,"settingFollowRedirects":"global","_type":"request"},{"_id":"req_38ecdf16a419429a8846bca7a33ee456","parentId":"fld_0ee2af5ae33e47718c90b22f378eb64d","modified":1697450612382,"created":1694965938150,"url":"http://127.0.0.1:4444/api/packages/6","name":"Delete a package (URL)","description":"","method":"DELETE","body":{},"parameters":[],"headers":[{"name":"User-Agent","value":"insomnia/2023.5.8","id":"pair_c010769d55424ef1964452be3b8b8570"},{"id":"pair_0f17ce21d3f04092b8c0c790fad42ff8","name":"Authorization","value":"eyJhbGciOiJIUzI1NiIsInR5cCI6IkpXVCJ9.eyJleHAiOjE2OTc1MzY4NzcsInVzZXJfaWQiOjR9.QXryXXI-AygMiLquRiYysft8tUyaNnw77ZeKQJCqwTA","description":""}],"authentication":{},"metaSortKey":-1694965694468.5,"isPrivate":false,"settingStoreCookies":true,"settingSendCookies":true,"settingDisableRenderRequestBody":false,"settingEncodeUrl":true,"settingRebuildPath":true,"settingFollowRedirects":"global","_type":"request"},{"_id":"req_0e8ff28de22f4aa9b8c5155c3313c243","parentId":"fld_0ee2af5ae33e47718c90b22f378eb64d","modified":1698785373970,"created":1694965670176,"url":"http://127.0.0.1:4444/api/packages/all","name":"List all packages","description":"","method":"GET","body":{},"parameters":[],"headers":[{"name":"User-Agent","value":"insomnia/2023.5.8","id":"pair_f15ec30592c44b7ca0c0fbd1fd187dab"},{"id":"pair_48389466be22444c8c2af75b3dbb4f3a","name":"Authorization","value":"eyJhbGciOiJIUzI1NiIsInR5cCI6IkpXVCJ9.eyJhY2Nlc3NfbGV2ZWwiOjMsImV4cCI6MTY5ODg3MTcyNSwidXNlcl9pZCI6NH0.knuHt5XYOSuDpLtMCft91pLGIVeIFmtDl0bcXiSSouE","description":""}],"authentication":{},"metaSortKey":-1694965670176,"isPrivate":false,"settingStoreCookies":true,"settingSendCookies":true,"settingDisableRenderRequestBody":false,"settingEncodeUrl":true,"settingRebuildPath":true,"settingFollowRedirects":"global","_type":"request"},{"_id":"req_e62757aa795d447990cf932219e0e98c","parentId":"fld_0ee2af5ae33e47718c90b22f378eb64d","modified":1697615456316,"created":1694966119377,"url":"http://127.0.0.1:4444/api/packages/get/x0Gpo0kt7A","name":"List a package info (URL)","description":"","method":"GET","body":{},"parameters":[],"headers":[{"name":"User-Agent","value":"insomnia/2023.5.8","id":"pair_27de62d0805b4983a56939081b42e751"}],"authentication":{},"metaSortKey":-1694965670126,"isPrivate":false,"settingStoreCookies":true,"settingSendCookies":true,"settingDisableRenderRequestBody":false,"settingEncodeUrl":true,"settingRebuildPath":true,"settingFollowRedirects":"global","_type":"request"},{"_id":"env_99d30891da4bdcebc63947a8fc17f076de878684","parentId":"wrk_scratchpad","modified":1696234075167,"created":1696234075167,"name":"Base Environment","data":{},"dataPropertyOrder":null,"color":null,"isPrivate":false,"metaSortKey":1696234075167,"_type":"environment"},{"_id":"jar_99d30891da4bdcebc63947a8fc17f076de878684","parentId":"wrk_scratchpad","modified":1696234075287,"created":1696234075287,"name":"Default Jar","cookies":[],"_type":"cookie_jar"}]}